<?xml version="1.0"?>
<Results version="1.0">
<ReportNode type="testrun">
<ReportNode type="Action">
<ReportNode type="Step">
<Data>
    <Name>Stop Run</Name>
    <Description>Run stopped by user.</Description>
    <StartTime>2021-08-23 13:08:05</StartTime>
    <Result>Information</Result>
    <Extension>
      <IconKey>ba9372d4e237407a8e8c31ac3be7b255</IconKey>
      <IsPlainTextNodeName>True</IsPlainTextNodeName>
    </Extension>
  </Data>
</ReportNode>
<Data>
    <Name>D365Application</Name>
    <Description />
    <StartTime>2021-08-23 13:07:47</StartTime>
    <Duration>18</Duration>
    <Result>Done</Result>
    <InputParameters />
    <Extension>
      <IconKey>4af7cf7e4f264d2fb99303938484cede</IconKey>
      <IsPlainTextNodeName>True</IsPlainTextNodeName>
    </Extension>
  </Data>
</ReportNode>
<ReportNode type="Step">
<Data>
    <Name>Stop Run</Name>
    <Description>Run stopped by user.</Description>
    <StartTime>2021-08-23 13:08:05</StartTime>
    <Result>Information</Result>
    <Extension>
      <IconKey>bbd10d97999f4907a37145b7655cac9a</IconKey>
      <IsPlainTextNodeName>True</IsPlainTextNodeName>
    </Extension>
  </Data>
</ReportNode>
<Data>
    <Name>MetCash_Flow_Demo</Name>
    <ToolName>Micro Focus Unified Functional Testing</ToolName>
    <ToolVersion>0</ToolVersion>
    <ToolVersionStringLiteral>15.0.2</ToolVersionStringLiteral>
    <Description />
    <StartTime>2021-08-23 13:07:44</StartTime>
    <Duration>21</Duration>
    <Result>Done</Result>
    <InputParameters />
    <Extension>
      <IconKey>33b269811ca74558853a69f9faf9ed58</IconKey>
      <IsPlainTextNodeName>True</IsPlainTextNodeName>
    </Extension>
    <Environment>
      <Timezone>+10:00:00</Timezone>
      <Locale>English (Australia)</Locale>
      <User>METCASH\gmko</User>
      <CpuInfo>Intel(R) Xeon(R) Silver 4114 CPU @ 2.20GHz</CpuInfo>
      <NumberOfCores>4</NumberOfCores>
      <TotalMemory>16383</TotalMemory>
      <HostName>metcash.com\IC2-IT-900026</HostName>
      <OSInfo>Windows 10</OSInfo>
    </Environment>
    <TestedApplications />
    <Links>
      <Link type="DataTable" reference="Default.xlsx" displayname="Default Data Table" />
    </Links>
  </Data>
</ReportNode>
<GeneralInfo>
    <ResultName>Res59</ResultName>
    <RunStartTime>2021-08-23 13:07:44</RunStartTime>
    <Timezone>+10:00:00</Timezone>
    <OrchestrationToolName>Micro Focus Unified Functional Testing</OrchestrationToolName>
    <OrchestrationToolVersion>0</OrchestrationToolVersion>
    <OrchestrationToolVersionStringLiteral>15.0.2</OrchestrationToolVersionStringLiteral>
  </GeneralInfo>
</Results>